cloudmesh_base/ConfigDict.py
cloudmesh_base/Shell.py
cloudmesh_base/ShellOriginal.py
cloudmesh_base/__init__.py
cloudmesh_base/debug.py
cloudmesh_base/dotdict.py
cloudmesh_base/get_os.py
cloudmesh_base/gitinfo.py
cloudmesh_base/hostlist.py
cloudmesh_base/i.py
cloudmesh_base/locations.py
cloudmesh_base/logger.py
cloudmesh_base/menu.py
cloudmesh_base/ping.py
cloudmesh_base/setup.py
cloudmesh_base/ssh_config.py
cloudmesh_base/stopwatch.py
cloudmesh_base/tables.py
cloudmesh_base/util.py
cloudmesh_base/version.py
cloudmesh_base/version_incr.py
cloudmesh_base/xshellutil.py
cloudmesh_base-3.5.2.dist-info/DESCRIPTION.rst
cloudmesh_base-3.5.2.dist-info/METADATA
cloudmesh_base-3.5.2.dist-info/RECORD
cloudmesh_base-3.5.2.dist-info/WHEEL
cloudmesh_base-3.5.2.dist-info/entry_points.txt
cloudmesh_base-3.5.2.dist-info/metadata.json
cloudmesh_base-3.5.2.dist-info/top_level.txt
cloudmesh_database/__init__.py
cloudmesh_database/dbconn.py
