Metadata-Version: 2.0
Name: cloudmesh-base
Version: 3.5.2
Summary: A set of simple base functions and classes useful for cloudmesh and other programs
Home-page: http://github.org/cloudmesh/base
Author: The Cloudmesh Team
Author-email: laszewski@gmail.com
License: UNKNOWN
Platform: UNKNOWN
Classifier: Intended Audience :: Developers
Classifier: Intended Audience :: Education
Classifier: Intended Audience :: Science/Research
Classifier: Development Status :: 4 - Beta
Classifier: Intended Audience :: Developers
Classifier: License :: OSI Approved :: Apache Software License
Classifier: Operating System :: MacOS :: MacOS X
Classifier: Operating System :: POSIX :: Linux
Classifier: Programming Language :: Python :: 2.7
Classifier: Topic :: Database
Classifier: Topic :: Software Development :: Libraries :: Python Modules
Classifier: Topic :: Scientific/Engineering
Classifier: Topic :: System :: Clustering
Classifier: Topic :: System :: Distributed Computing
Classifier: Topic :: System :: Boot
Classifier: Topic :: System :: Systems Administration
Classifier: Framework :: Flask
Classifier: Environment :: OpenStack
Requires-Dist: docopt
Requires-Dist: future
Requires-Dist: gitchangelog
Requires-Dist: nose
Requires-Dist: prettytable
Requires-Dist: pyaml
Requires-Dist: pytimeparse
Requires-Dist: pyyaml
Requires-Dist: simplejson
Requires-Dist: tox
Requires-Dist: wheel
